taskstate/__init__.py
taskstate/apps.py
taskstate/consumers.py
taskstate/middleware.py
taskstate/models.py
taskstate/receivers.py
taskstate/routing.py
taskstate/signals.py
taskstate/tasks.py
taskstate/management/__init__.py
taskstate/management/commands/__init__.py
taskstate/management/commands/clear_tasks.py
taskstate/migrations/0001_initial.py
taskstate/migrations/0002_task_seen_at.py
taskstate/migrations/0003_task_results.py
taskstate/migrations/__init__.py
taskstate/static/taskstate/get_task_status.js
taskstate/templates/taskstate/task_list.html
taskstate/tests/__init__.py
taskstate/tests/tests.py
dramatiq_taskstate-0.3.4.dist-info/LICENSE
dramatiq_taskstate-0.3.4.dist-info/METADATA
dramatiq_taskstate-0.3.4.dist-info/WHEEL
dramatiq_taskstate-0.3.4.dist-info/top_level.txt
dramatiq_taskstate-0.3.4.dist-info/RECORD
