Metadata-Version: 2.1
Name: dramatiq-taskstate
Version: 0.3.4
Summary: A middleware for Dramatiq (for Django) that keeps track of task state only when you need it to.
Home-page: https://github.com/armandtvz/dramatiq-taskstate
Author: Armandt van Zyl
Author-email: armandtvz@gmail.com
License: GPL-3.0
Platform: UNKNOWN
Classifier: Development Status :: 4 - Beta
Classifier: Environment :: Web Environment
Classifier: Framework :: Django
Classifier: Framework :: Django :: 3.0
Classifier: Intended Audience :: Developers
Classifier: License :: OSI Approved :: GNU General Public License v3 (GPLv3)
Classifier: Operating System :: OS Independent
Classifier: Programming Language :: Python
Classifier: Programming Language :: Python :: 3
Classifier: Programming Language :: Python :: 3 :: Only
Classifier: Topic :: Internet :: WWW/HTTP
Requires-Python: >=3.6
License-File: LICENSE
Requires-Dist: Django (>=3.2)
Requires-Dist: dramatiq (>=1.11)
Requires-Dist: django-dramatiq (>=0.10)
Requires-Dist: psycopg2-binary
Provides-Extra: websockets
Requires-Dist: channels ; extra == 'websockets'
Requires-Dist: redis ; extra == 'websockets'
